examples/BouncingBallStructure.xml
examples/DrivingForce.fmu
examples/ForcedOscillator.xml
examples/ForcedOscillator6D.xml
examples/HarmonicOscillator.fmu
examples/HarmonicOscillator6D.fmu
examples/TimeTableStructure.xml
examples/__init__.py
examples/axle.py
examples/axle_fmu.py
examples/bouncing_ball_3d.py
examples/bouncing_ball_3d_pythonfmu.py
examples/driving_force_fmu.py
examples/oscillator.py
examples/oscillator_6d.py
examples/oscillator_6dof_fmu.py
examples/oscillator_fmu.py
examples/oscillator_xd.py
examples/time_table.py
examples/time_table_fmu.py
component_model/__init__.py
component_model/enums.py
component_model/model.py
component_model/plotter.py
component_model/py.typed
component_model/variable.py
component_model/variable_naming.py
component_model/utils/__init__.py
component_model/utils/analysis.py
component_model/utils/controls.py
component_model/utils/fmu.py
component_model/utils/transform.py
component_model/utils/xml.py
component_model-0.3.0.dist-info/METADATA
component_model-0.3.0.dist-info/WHEEL
component_model-0.3.0.dist-info/licenses/LICENSE
component_model-0.3.0.dist-info/RECORD
