Metadata-Version: 2.4
Name: component-model
Version: 0.3.0
Summary: Constructs a Functional Mockup Interface component model from a python script (fulfilling some requirements).
Project-URL: Homepage, https://github.com/dnv-opensource/component-model
Project-URL: Documentation, https://dnv-opensource.github.io/component-model/README.html
Project-URL: Repository, https://github.com/dnv-opensource/component-model.git
Project-URL: Issues, https://github.com/dnv-opensource/component-model/issues
Project-URL: Changelog, https://github.com/dnv-opensource/component-model/blob/main/CHANGELOG.md
Author-email: Siegfried Eisinger <Siegfried.Eisinger@dnv.com>
License: MIT License
License-File: LICENSE
Keywords: FMI,OSP,model,simulation
Classifier: Development Status :: 4 - Beta
Classifier: Environment :: Console
Classifier: Intended Audience :: Developers
Classifier: Intended Audience :: Science/Research
Classifier: License :: OSI Approved :: MIT License
Classifier: Operating System :: MacOS
Classifier: Operating System :: Microsoft :: Windows
Classifier: Operating System :: POSIX :: Linux
Classifier: Programming Language :: Python :: 3.10
Classifier: Programming Language :: Python :: 3.11
Classifier: Programming Language :: Python :: 3.12
Classifier: Topic :: Scientific/Engineering
Classifier: Topic :: Software Development :: Libraries :: Python Modules
Requires-Python: >=3.11
Requires-Dist: flexparser>=0.4
Requires-Dist: jsonpath-ng>=1.7.0
Requires-Dist: numpy>=2.0
Requires-Dist: pint>=0.24.4
Requires-Dist: pythonfmu==0.6.9
Provides-Extra: editor
Provides-Extra: rest
Requires-Dist: docutils>=0.21; extra == 'rest'
Provides-Extra: tests
Requires-Dist: fmpy==0.3.21; extra == 'tests'
Requires-Dist: matplotlib>=3.9.1; extra == 'tests'
Requires-Dist: plotly>=6.0.1; extra == 'tests'
Requires-Dist: scipy>=1.15.1; extra == 'tests'
